{
  "$schema": "https://json-schema.org/draft/2020-12/schema",
  "$id": "https://bami/schemas/intermediate-slide-schema.json",
  "title": "BAMi Intermediate Slide Schema",
  "description": "Bridge between content intent and both renderers (Slidev Branch A, python-pptx Branch B). Serves as the JSON-first intermediate representation that decouples content from presentation.",
  "type": "object",
  "required": ["schema_version", "meta", "slides"],
  "properties": {
    "schema_version": {
      "type": "string",
      "const": "1.0.0",
      "description": "Semver string. Bump major on breaking changes (renderers reject unknown versions via const)."
    },
    "meta": {
      "type": "object",
      "required": ["title"],
      "properties": {
        "title":    { "type": "string", "description": "Deck title (displayed in browser tab / metadata)" },
        "subtitle": { "type": "string" },
        "client":   { "type": "string" },
        "date":     { "type": "string" }
      },
      "additionalProperties": false
    },
    "slides": {
      "type": "array",
      "minItems": 1,
      "items": { "$ref": "#/$defs/slide" }
    }
  },
  "additionalProperties": false,
  "$defs": {
    "slide": {
      "type": "object",
      "required": ["type"],
      "properties": {
        "type": {
          "enum": ["cover", "content", "closing"],
          "description": "Maps directly to Slidev frontmatter layout:. cover/closing use props for chrome slots; content uses title + components/body."
        },
        "title": {
          "type": "string",
          "description": "Content slide title (required on type=content). Maps to the black title bar chrome slot."
        },
        "props": {
          "type": "object",
          "description": "Chrome slot values for cover/closing. Keys match design_tokens.yaml slot names 1:1. For cover: eyebrow, kicker, hero, subtitle, steps[]. For closing: eyebrow, hero, subtitle, step_numbers[], step_titles[], step_bodies[], contact."
        },
        "components": {
          "type": "array",
          "items": { "$ref": "#/$defs/component_invocation" },
          "description": "Ordered list of Slidev Vue component invocations. Rendered in sequence after body."
        },
        "body": {
          "type": "string",
          "description": "Raw Markdown body (escape hatch for simple slides). Rendered before components."
        },
        "section": {
          "type": "string",
          "description": "Teal-colored section label (e.g. 'THE CONTEXT'). Rendered above subheading in body area. Template pattern."
        },
        "subheading": {
          "type": "string",
          "description": "Dark bold heading below section label (e.g. 'Copilot is already in your tenant...')."
        },
        "bodytext": {
          "type": "string",
          "description": "Body paragraph below subheading (e.g. 'What is missing is an agile way to assess...')."
        }
      },
      "additionalProperties": false
    },
    "component_invocation": {
      "type": "object",
      "required": ["component", "props"],
      "properties": {
        "component": {
          "type": "string",
          "minLength": 1,
          "description": "PascalCase Vue component name (e.g. 'TierPricingCards'). Must be registered in schemas/components/registry.json."
        },
        "props": {
          "type": "object",
          "description": "Component props. Schema validates structure only (object type). Semantic validation (required props, types) happens via Component Registry (schemas/components/) at the reviewer stage."
        }
      },
      "additionalProperties": false
    }
  }
}
